{"cameraMode":{"drawMode":0,"name":"Shaded","section":"Shading Mode"},"sceneLighting":true,"audioPlay":false,"sceneViewState":{"m_AlwaysRefresh":false,"showFog":true,"showSkybox":true,"showFlares":true,"showImageEffects":true,"showParticleSystems":true,"showVisualEffectGraphs":true,"m_FxEnabled":true},"in2DMode":false,"pivot":{"x":65.05752563476563,"y":4.455406188964844,"z":8.951705932617188},"rotation":{"x":0.05089646577835083,"y":0.882369875907898,"z":-0.09875340759754181,"w":0.4575662910938263},"size":41.282493591308597,"orthographic":false}